CHANGES.txt
LICENSE.txt
MANIFEST.in
Makefile
README.txt
setup.cfg
setup.py
smc.bibencodings.egg-info/PKG-INFO
smc.bibencodings.egg-info/SOURCES.txt
smc.bibencodings.egg-info/dependency_links.txt
smc.bibencodings.egg-info/namespace_packages.txt
smc.bibencodings.egg-info/top_level.txt
smc.bibencodings.egg-info/zip-safe
smc/bibencodings/__init__.py
smc/bibencodings/iso5426.py
smc/bibencodings/marc.py
smc/bibencodings/parse.py
smc/bibencodings/tests.py
smc/bibencodings/utils.py
smc/bibencodings/testdata/record_0.mab
smc/bibencodings/testdata/record_0.xml
smc/bibencodings/testdata/record_1.mab
smc/bibencodings/testdata/record_1.xml
smc/bibencodings/testdata/record_2.mab
smc/bibencodings/testdata/record_2.xml
smc/bibencodings/testdata/record_3.mab
smc/bibencodings/testdata/record_3.xml
smc/bibencodings/testdata/record_4.mab
smc/bibencodings/testdata/record_4.xml
smc/bibencodings/testdata/record_5.mab
smc/bibencodings/testdata/record_5.xml
smc/bibencodings/testdata/record_50_70_diskform_off.mab
smc/bibencodings/testdata/record_50_70_diskform_off.xml
smc/bibencodings/testdata/record_6.mab
smc/bibencodings/testdata/record_6.xml
smc/bibencodings/testdata/record_7.mab
smc/bibencodings/testdata/record_7.xml
smc/bibencodings/testdata/record_8.mab
smc/bibencodings/testdata/record_8.xml
smc/bibencodings/testdata/record_9.mab
smc/bibencodings/testdata/record_9.xml
smc/bibencodings/testdata/record_brokenplaintext.mab
smc/bibencodings/testdata/record_brokenplaintext.xml
smc/bibencodings/testdata/record_brokenplaintext2.mab
smc/bibencodings/testdata/record_brokenplaintext2.xml
smc/bibencodings/testdata/record_hebis_marc.mab
smc/bibencodings/testdata/record_hebis_marc.xml
smc/bibencodings/testdata/record_keller.mab
smc/bibencodings/testdata/record_keller.xml
smc/bibencodings/testdata/record_lok.mab
smc/bibencodings/testdata/record_lok.xml
smc/bibencodings/testdata/record_plaintext.mab
smc/bibencodings/testdata/record_plaintext.xml