Metadata-Version: 1.1
Name: smc.bibencodings
Version: 0.1
Summary: UNKNOWN
Home-page: https://bitbucket.org/tiran/smc.bibencodings
Author: Christian Heimes
Author-email: c.heimes@semantics.de
License: BSD
Keywords: encoding codec bibliographic opac mab2 iso-5426 marc ansel
Platform: UNKNOWN
Classifier: Development Status :: 4 - Beta
Classifier: Intended Audience :: Developers
Classifier: License :: OSI Approved :: BSD License
Classifier: Natural Language :: English
Classifier: Operating System :: OS Independent
Classifier: Programming Language :: Python
Classifier: Programming Language :: Python :: 2
Classifier: Programming Language :: Python :: 2.6
Classifier: Programming Language :: Python :: 2.7
Classifier: Programming Language :: Python :: 3
Classifier: Programming Language :: Python :: 3.1
Classifier: Programming Language :: Python :: 3.2
Classifier: Programming Language :: Python :: 3.3
Classifier: Topic :: Communications
Classifier: Topic :: Software Development :: Libraries :: Python Modules
Classifier: Topic :: Text Processing :: General
